conda-recipe/meta.yaml
conda-recipe/run_test.py
data/datasets.json
docs/QUICK_START.md
docs/examples/basic_usage.py
docs/examples/batch_download.py
neurodatahub/__init__.py
neurodatahub/auth.py
neurodatahub/cli.py
neurodatahub/config.py
neurodatahub/datasets.py
neurodatahub/downloader.py
neurodatahub/exceptions.py
neurodatahub/ida_flow.py
neurodatahub/logging_config.py
neurodatahub/performance.py
neurodatahub/progress.py
neurodatahub/utils.py
neurodatahub/validation.py
neurodatahub/data/__init__.py
neurodatahub/data/datasets.json
neurodatahub_cli-1.0.2.dist-info/licenses/LICENSE
scripts/setup_dev.py
tests/__init__.py
tests/conftest.py
tests/integration/test_full_workflow.py
tests/unit/test_cli.py
tests/unit/test_datasets.py
tests/unit/test_downloader.py
tests/unit/test_utils.py
neurodatahub_cli-1.0.2.dist-info/METADATA
neurodatahub_cli-1.0.2.dist-info/WHEEL
neurodatahub_cli-1.0.2.dist-info/entry_points.txt
neurodatahub_cli-1.0.2.dist-info/top_level.txt
neurodatahub_cli-1.0.2.dist-info/RECORD
