Metadata-Version: 2.4
Name: neurodatahub-cli
Version: 1.0.2
Summary: A command-line interface for downloading neuroimaging datasets
Author-email: Ninad Aithal <reachninadaithal@gmail.com>
License: MIT
Project-URL: Homepage, https://blackpearl006.github.io/NeuroDataHub/
Project-URL: Repository, https://github.com/blackpearl006/neurodatahub-cli
Project-URL: Documentation, https://blackpearl006.github.io/NeuroDataHub/
Project-URL: Bug Reports, https://github.com/blackpearl006/neurodatahub-cli/issues
Keywords: neuroimaging,datasets,cli,neuroscience,mri,brain
Classifier: Development Status :: 4 - Beta
Classifier: Intended Audience :: Science/Research
Classifier: License :: OSI Approved :: MIT License
Classifier: Operating System :: OS Independent
Classifier: Programming Language :: Python :: 3
Classifier: Programming Language :: Python :: 3.8
Classifier: Programming Language :: Python :: 3.9
Classifier: Programming Language :: Python :: 3.10
Classifier: Programming Language :: Python :: 3.11
Classifier: Programming Language :: Python :: 3.12
Classifier: Topic :: Scientific/Engineering :: Medical Science Apps.
Classifier: Topic :: System :: Archiving
Classifier: Topic :: Utilities
Requires-Python: >=3.8
License-File: LICENSE
Requires-Dist: click>=8.0
Requires-Dist: requests>=2.25.0
Requires-Dist: selenium>=4.0.0
Requires-Dist: tqdm>=4.60.0
Requires-Dist: rich>=12.0.0
Requires-Dist: colorama>=0.4.4
Requires-Dist: pyyaml>=6.0
Provides-Extra: dev
Requires-Dist: pytest>=7.0; extra == "dev"
Requires-Dist: pytest-cov>=4.0; extra == "dev"
Requires-Dist: black>=22.0; extra == "dev"
Requires-Dist: isort>=5.10; extra == "dev"
Requires-Dist: flake8>=5.0; extra == "dev"
Requires-Dist: mypy>=1.0; extra == "dev"
Requires-Dist: pre-commit>=3.0.0; extra == "dev"
Requires-Dist: bandit>=1.7.0; extra == "dev"
Requires-Dist: build>=0.10.0; extra == "dev"
Requires-Dist: twine>=4.0.0; extra == "dev"
Provides-Extra: performance
Requires-Dist: psutil>=5.9.0; extra == "performance"
Requires-Dist: aiohttp>=3.8.0; extra == "performance"
Requires-Dist: aiofiles>=23.0.0; extra == "performance"
Dynamic: license-file
